[
    {
        "generation": "generation-i",
        "unavailable_types": [
            "steel",
            "dark",
            "fairy"
        ],
        "changed_efficiencies": [
            {
                "attack_type": "poison",
                "defense_type": "bug",
                "new_value": 2
            },
            {
                "attack_type": "bug",
                "defense_type": "poison",
                "new_value": 2
            },
            {
                "attack_type": "ghost",
                "defense_type": "psychic",
                "new_value": 0
            },
            {
                "attack_type": "ice",
                "defense_type": "fire",
                "new_value": 1
            },
            {
                "attack_type": "ghost",
                "defense_type": "steel",
                "new_value": 0.5
            },
            {
                "attack_type": "dark",
                "defense_type": "steel",
                "new_value": 0.5
            }
        ]
    },
    {
        "generation": "generation-ii",
        "unavailable_types": [
            "fairy"
        ],
        "changed_efficiencies": [
            {
                "attack_type": "ghost",
                "defense_type": "steel",
                "new_value": 0.5
            },
            {
                "attack_type": "dark",
                "defense_type": "steel",
                "new_value": 0.5
            }
        ]
    },
    {
        "generation": "generation-iii",
        "unavailable_types": [
            "fairy"
        ],
        "changed_efficiencies": [
            {
                "attack_type": "ghost",
                "defense_type": "steel",
                "new_value": 0.5
            },
            {
                "attack_type": "dark",
                "defense_type": "steel",
                "new_value": 0.5
            }
        ]
    },
    {
        "generation": "generation-iv",
        "unavailable_types": [
            "fairy"
        ],
        "changed_efficiencies": [
            {
                "attack_type": "ghost",
                "defense_type": "steel",
                "new_value": 0.5
            },
            {
                "attack_type": "dark",
                "defense_type": "steel",
                "new_value": 0.5
            }
        ]
    },
    {
        "generation": "generation-v",
        "unavailable_types": [
            "fairy"
        ],
        "changed_efficiencies": [
            {
                "attack_type": "ghost",
                "defense_type": "steel",
                "new_value": 0.5
            },
            {
                "attack_type": "dark",
                "defense_type": "steel",
                "new_value": 0.5
            }
        ]
    },
    {
        "generation": "generation-vi",
        "unavailable_types": [],
        "changed_efficiencies": []
    },
    {
        "generation": "generation-vii",
        "unavailable_types": [],
        "changed_efficiencies": []
    },
    {
        "generation": "generation-viii",
        "unavailable_types": [],
        "changed_efficiencies": []
    }
]